ExtPenPy/ExtPenPy.py
ExtPenPy/Mobile.py
ExtPenPy/aws.py
ExtPenPy/azure.py
ExtPenPy/gcp.py
ExtPenPy/web.py
ExtPenPy-1.3.dist-info/METADATA
ExtPenPy-1.3.dist-info/WHEEL
ExtPenPy-1.3.dist-info/entry_points.txt
ExtPenPy-1.3.dist-info/top_level.txt
ExtPenPy-1.3.dist-info/RECORD
