Metadata-Version: 2.1
Name: ExtPenPy
Version: 1.3
Summary: ExtPenPy is a tool that will help you finalizing your recon phase faster.
Home-page: https://github.com/maliktawfiq/ExtPenPy
Author: Anas Shlool, MalikTawfiq, Yanal Abuseini
Author-email: anasshlool11@gmail.com
Classifier: Programming Language :: Python :: 3
Classifier: License :: OSI Approved :: MIT License
Classifier: Operating System :: OS Independent
Requires-Python: >=3.10
Requires-Dist: androguard
Requires-Dist: apk2java
Requires-Dist: dnspython
Requires-Dist: python-whois
Requires-Dist: requests
Requires-Dist: whois
Requires-Dist: webdriver-manager
Requires-Dist: Selenium
Requires-Dist: more-itertools
